materials_visualization/__init__.py
materials_visualization/materials_visualization.py
materials_visualization-0.1.5.dist-info/LICENSE.md
materials_visualization-0.1.5.dist-info/METADATA
materials_visualization-0.1.5.dist-info/WHEEL
materials_visualization-0.1.5.dist-info/top_level.txt
materials_visualization-0.1.5.dist-info/RECORD
