Metadata-Version: 2.1
Name: materials_visualization
Version: 0.1.5
Summary: Routines to visualize atomic models in jupyter
Home-page: https://github.com/kevinwhitham/materials_visualization.git
Author: Kevin Whitham
Author-email: kevin.whitham@gmail.com
Classifier: Programming Language :: Python :: 3
Classifier: License :: OSI Approved :: GNU General Public License v3 or later (GPLv3+)
Classifier: Operating System :: OS Independent
Requires-Python: >=3
License-File: LICENSE.md
Requires-Dist: perovskite-intercalation >=0.0.6
Requires-Dist: nglview >=2.7.7
Requires-Dist: ase >=3.21.1
Requires-Dist: ipywidgets >=7.5.1
Requires-Dist: numpy >=1.20.2
Requires-Dist: gpaw >=20.10.0
